pydantic_ai_nova/__init__.py
pydantic_ai_nova/nova.py
pydantic_ai_nova-0.2.0.dist-info/METADATA
pydantic_ai_nova-0.2.0.dist-info/WHEEL
pydantic_ai_nova-0.2.0.dist-info/licenses/LICENSE
pydantic_ai_nova-0.2.0.dist-info/RECORD
