Metadata-Version: 2.4
Name: pydantic-ai-nova
Version: 0.2.0
Summary: Amazon Bedrock Nova model integration for pydantic-ai
Project-URL: Homepage, https://github.com/speetchai/speetchai-pydantic-ai-nova
Project-URL: Bug Tracker, https://github.com/speetchai/speetchai-pydantic-ai-nova/issues
Author-email: Bilal Ahmed <ba@speetch.ai>
License-File: LICENSE
Classifier: License :: OSI Approved :: MIT License
Classifier: Operating System :: OS Independent
Classifier: Programming Language :: Python :: 3
Requires-Python: >=3.8
Requires-Dist: boto3>=1.28.0
Requires-Dist: pydantic-ai==0.0.18
Provides-Extra: dev
Requires-Dist: pytest-asyncio>=0.21.0; extra == 'dev'
Requires-Dist: pytest>=7.0.0; extra == 'dev'
